{"data":{"mal_id":1028,"url":"https:\/\/myanimelist.net\/anime\/1028\/Arete_Hime","images":{"jpg":{"image_url":"https:\/\/cdn.myanimelist.net\/images\/anime\/10\/4327.jpg","small_image_url":"https:\/\/cdn.myanimelist.net\/images\/anime\/10\/4327t.jpg","large_image_url":"https:\/\/cdn.myanimelist.net\/images\/anime\/10\/4327l.jpg"},"webp":{"image_url":"https:\/\/cdn.myanimelist.net\/images\/anime\/10\/4327.webp","small_image_url":"https:\/\/cdn.myanimelist.net\/images\/anime\/10\/4327t.webp","large_image_url":"https:\/\/cdn.myanimelist.net\/images\/anime\/10\/4327l.webp"}},"trailer":{"youtube_id":"kobQELVQkNs","url":"https:\/\/www.youtube.com\/watch?v=kobQELVQkNs","embed_url":"https:\/\/www.youtube.com\/embed\/kobQELVQkNs?enablejsapi=1&wmode=opaque&autoplay=1","images":{"image_url":"https:\/\/img.youtube.com\/vi\/kobQELVQkNs\/default.jpg","small_image_url":"https:\/\/img.youtube.com\/vi\/kobQELVQkNs\/sddefault.jpg","medium_image_url":"https:\/\/img.youtube.com\/vi\/kobQELVQkNs\/mqdefault.jpg","large_image_url":"https:\/\/img.youtube.com\/vi\/kobQELVQkNs\/hqdefault.jpg","maximum_image_url":"https:\/\/img.youtube.com\/vi\/kobQELVQkNs\/maxresdefault.jpg"}},"approved":true,"titles":[{"type":"Default","title":"Arete Hime"},{"type":"Synonym","title":"Arite Hime"},{"type":"Synonym","title":"The Adventure of Princess Arete"},{"type":"Synonym","title":"Arete-hime"},{"type":"Japanese","title":"\u30a2\u30ea\u30fc\u30c6\u59eb"},{"type":"English","title":"Princess Arete"},{"type":"Spanish","title":"Princesa Arete"},{"type":"French","title":"Princess Arete"}],"title":"Arete Hime","title_english":"Princess Arete","title_japanese":"\u30a2\u30ea\u30fc\u30c6\u59eb","title_synonyms":["Arite Hime","The Adventure of Princess Arete","Arete-hime"],"type":"Movie","source":"Novel","episodes":1,"status":"Finished Airing","airing":false,"aired":{"from":"2001-07-21T00:00:00+00:00","to":null,"prop":{"from":{"day":21,"month":7,"year":2001},"to":{"day":null,"month":null,"year":null}},"string":"Jul 21, 2001"},"duration":"1 hr 44 min","rating":"G - All Ages","score":6.89,"scored_by":4705,"rank":4605,"popularity":5535,"members":13274,"favorites":52,"synopsis":"Confined in the castle tower by her father, princess Arete spends her days watching the world outside her window. Sometimes she seeks out to watch the common people at work. The knights of the kingdom compete for the right to marry her and rule the land by competing to see who can find powerful magic objects made by a long dead race of sorcerers. Arete wants none of this. She longs to meet the common people and travel to exotic lands she has only seen in the books she keeps hidden under her bed. One day the sorcerer Boax arrives in a fantastic flying machine and offers to take Arete as his wife and transform her into a proper princess.\n\n(Source: ANN)","background":null,"season":null,"year":null,"broadcast":{"day":null,"time":null,"timezone":null,"string":null},"producers":[{"mal_id":53,"type":"anime","name":"Dentsu","url":"https:\/\/myanimelist.net\/anime\/producer\/53\/Dentsu"},{"mal_id":170,"type":"anime","name":"Imagica","url":"https:\/\/myanimelist.net\/anime\/producer\/170\/Imagica"},{"mal_id":1430,"type":"anime","name":"Shogakukan","url":"https:\/\/myanimelist.net\/anime\/producer\/1430\/Shogakukan"},{"mal_id":1584,"type":"anime","name":"Beyond C.","url":"https:\/\/myanimelist.net\/anime\/producer\/1584\/Beyond_C"},{"mal_id":1585,"type":"anime","name":"Nichion","url":"https:\/\/myanimelist.net\/anime\/producer\/1585\/Nichion"}],"licensors":[],"studios":[{"mal_id":13,"type":"anime","name":"Studio 4\u00b0C","url":"https:\/\/myanimelist.net\/anime\/producer\/13\/Studio_4%C2%B0C"}],"genres":[{"mal_id":10,"type":"anime","name":"Fantasy","url":"https:\/\/myanimelist.net\/anime\/genre\/10\/Fantasy"}],"explicit_genres":[],"themes":[],"demographics":[],"relations":[],"theme":{"openings":["\"\u041a\u0440\u0430\u0441\u043d\u043e \u0421\u043e\u043b\u043d\u0446\u0435 (Krasno Solntse)\" by Origa"],"endings":["\"kin'iro no tsubasa (\u91d1\u8272\u306e\u7ffc)\" by Taeko Oonuki"]},"external":[{"name":"Official Site","url":"http:\/\/www.arete.jp\/arete\/"},{"name":"AniDB","url":"https:\/\/anidb.net\/perl-bin\/animedb.pl?show=anime&aid=1190"},{"name":"ANN","url":"https:\/\/www.animenewsnetwork.com\/encyclopedia\/anime.php?id=2163"}],"streaming":[]}}