{"data":{"mal_id":2039,"url":"https:\/\/myanimelist.net\/anime\/2039\/Mahou_no_Yousei_Persia","images":{"jpg":{"image_url":"https:\/\/cdn.myanimelist.net\/images\/anime\/8\/41447.jpg","small_image_url":"https:\/\/cdn.myanimelist.net\/images\/anime\/8\/41447t.jpg","large_image_url":"https:\/\/cdn.myanimelist.net\/images\/anime\/8\/41447l.jpg"},"webp":{"image_url":"https:\/\/cdn.myanimelist.net\/images\/anime\/8\/41447.webp","small_image_url":"https:\/\/cdn.myanimelist.net\/images\/anime\/8\/41447t.webp","large_image_url":"https:\/\/cdn.myanimelist.net\/images\/anime\/8\/41447l.webp"}},"trailer":{"youtube_id":null,"url":null,"embed_url":null,"images":{"image_url":null,"small_image_url":null,"medium_image_url":null,"large_image_url":null,"maximum_image_url":null}},"approved":true,"titles":[{"type":"Default","title":"Mahou no Yousei Persia"},{"type":"Synonym","title":"Magical Fairy Persia"},{"type":"Synonym","title":"Magical Fairy Perusha"},{"type":"Japanese","title":"\u9b54\u6cd5\u306e\u5996\u7cbe \u30da\u30eb\u30b7\u30e3"},{"type":"English","title":"Persia the Magic Fairy"}],"title":"Mahou no Yousei Persia","title_english":"Persia the Magic Fairy","title_japanese":"\u9b54\u6cd5\u306e\u5996\u7cbe \u30da\u30eb\u30b7\u30e3","title_synonyms":["Magical Fairy Persia","Magical Fairy Perusha"],"type":"TV","source":"Original","episodes":48,"status":"Finished Airing","airing":false,"aired":{"from":"1984-07-06T00:00:00+00:00","to":"1985-05-31T00:00:00+00:00","prop":{"from":{"day":6,"month":7,"year":1984},"to":{"day":31,"month":5,"year":1985}},"string":"Jul 6, 1984 to May 31, 1985"},"duration":"24 min per ep","rating":"PG - Children","score":7.32,"scored_by":904,"rank":2543,"popularity":9286,"members":3439,"favorites":24,"synopsis":"11-year-old Persia has grown up alongside the animals on the Serengeti plains of Africa. Twins Riki and Gaku Muroi and their grandfather, Gouken, bring Persia to Japan with them, where she will live with a couple (who Persia calls Mama and Papa) that own a grocery store. During the flight to Japan, Persia finds herself in the \"Lovely Dream\" where she meets the Fairy Queen, who explains that the Lovely Dream is in danger and requests Persia's help. Giving Persia a magical headband (which can also summon a magical baton) that allows her to transform into a teenage girl, connecting her to the Lovely Dream and allowing her to use magic. She is sent with three kappa back into the regular world with the mission of collecting love energy to thaw the frozen Lovely Dream. If Persia fails her task of collecting love energy or if someone catches her using magic, Riki and Gaku will be transformed into women.\n\n(Source: ANN)","background":null,"season":"summer","year":1984,"broadcast":{"day":null,"time":null,"timezone":null,"string":"Unknown"},"producers":[],"licensors":[],"studios":[{"mal_id":1,"type":"anime","name":"Pierrot","url":"https:\/\/myanimelist.net\/anime\/producer\/1\/Pierrot"}],"genres":[{"mal_id":4,"type":"anime","name":"Comedy","url":"https:\/\/myanimelist.net\/anime\/genre\/4\/Comedy"}],"explicit_genres":[],"themes":[{"mal_id":66,"type":"anime","name":"Mahou Shoujo","url":"https:\/\/myanimelist.net\/anime\/genre\/66\/Mahou_Shoujo"}],"demographics":[],"relations":[{"relation":"Adaptation","entry":[{"mal_id":9883,"type":"manga","name":"Persia ga Suki!","url":"https:\/\/myanimelist.net\/manga\/9883\/Persia_ga_Suki"}]},{"relation":"Spin-off","entry":[{"mal_id":2080,"type":"anime","name":"Majokko Club Yoningumi: A Kuukan kara no Alien X","url":"https:\/\/myanimelist.net\/anime\/2080\/Majokko_Club_Yoningumi__A_Kuukan_kara_no_Alien_X"},{"mal_id":5246,"type":"anime","name":"Adesugata Mahou no Sannin Musume","url":"https:\/\/myanimelist.net\/anime\/5246\/Adesugata_Mahou_no_Sannin_Musume"}]},{"relation":"Prequel","entry":[{"mal_id":22239,"type":"anime","name":"Mahou no Yousei Persia Pilot","url":"https:\/\/myanimelist.net\/anime\/22239\/Mahou_no_Yousei_Persia_Pilot"}]},{"relation":"Other","entry":[{"mal_id":22293,"type":"anime","name":"Mahou no Yousei Persia: Escape!","url":"https:\/\/myanimelist.net\/anime\/22293\/Mahou_no_Yousei_Persia__Escape"}]},{"relation":"Summary","entry":[{"mal_id":35519,"type":"anime","name":"Mahou no Yousei Persia: Kaiten Mokuba","url":"https:\/\/myanimelist.net\/anime\/35519\/Mahou_no_Yousei_Persia__Kaiten_Mokuba"}]}],"theme":{"openings":["1: \"Mishiranu Kuni no Tripper (\u898b\u77e5\u3089\u306c\u56fd\u306e\u30c8\u30ea\u30c3\u30d1\u30fc)\" by Maiko Okamoto (eps 1-31)","2: \"Osharemesaruna (\u304a\u3057\u3083\u308c\u3081\u3055\u308b\u306a)\" by MIMA (eps 32-48)"],"endings":["1: \"Lovely Dream (\u30e9\u30d6\u30ea\u30fc\u30c9\u30ea\u30fc\u30e0)\" by Maiko Okamoto (eps 1-31)","2: \"Daisuki Simba (\u3060\u3044\u3059\u304d\u30b7\u30f3\u30d0)\" by Miina Tominaga (eps 32-48)"]},"external":[{"name":"Official Site","url":"http:\/\/pierrot.jp\/title\/magicgirl\/cate02.html"},{"name":"AniDB","url":"https:\/\/anidb.net\/perl-bin\/animedb.pl?show=anime&aid=499"},{"name":"ANN","url":"https:\/\/www.animenewsnetwork.com\/encyclopedia\/anime.php?id=1681"}],"streaming":[]}}