{"data":{"mal_id":2386,"url":"https:\/\/myanimelist.net\/anime\/2386\/One_Piece__Yume_no_Soccer_Ou","images":{"jpg":{"image_url":"https:\/\/cdn.myanimelist.net\/images\/anime\/4\/70587.jpg","small_image_url":"https:\/\/cdn.myanimelist.net\/images\/anime\/4\/70587t.jpg","large_image_url":"https:\/\/cdn.myanimelist.net\/images\/anime\/4\/70587l.jpg"},"webp":{"image_url":"https:\/\/cdn.myanimelist.net\/images\/anime\/4\/70587.webp","small_image_url":"https:\/\/cdn.myanimelist.net\/images\/anime\/4\/70587t.webp","large_image_url":"https:\/\/cdn.myanimelist.net\/images\/anime\/4\/70587l.webp"}},"trailer":{"youtube_id":null,"url":null,"embed_url":null,"images":{"image_url":null,"small_image_url":null,"medium_image_url":null,"large_image_url":null,"maximum_image_url":null}},"approved":true,"titles":[{"type":"Default","title":"One Piece: Yume no Soccer Ou!"},{"type":"Synonym","title":"One Piece: Soccer King of Dreams"},{"type":"Japanese","title":"\u30ef\u30f3\u30d4\u30fc\u30b9 \u5922\u306e\u30b5\u30c3\u30ab\u30fc\u738b!"},{"type":"English","title":"One Piece: Dream Soccer King"}],"title":"One Piece: Yume no Soccer Ou!","title_english":"One Piece: Dream Soccer King","title_japanese":"\u30ef\u30f3\u30d4\u30fc\u30b9 \u5922\u306e\u30b5\u30c3\u30ab\u30fc\u738b!","title_synonyms":["One Piece: Soccer King of Dreams"],"type":"Movie","source":"Manga","episodes":1,"status":"Finished Airing","airing":false,"aired":{"from":"2002-03-02T00:00:00+00:00","to":null,"prop":{"from":{"day":2,"month":3,"year":2002},"to":{"day":null,"month":null,"year":null}},"string":"Mar 2, 2002"},"duration":"5 min","rating":"PG-13 - Teens 13 or older","score":7.1,"scored_by":24519,"rank":3654,"popularity":3186,"members":44848,"favorites":19,"synopsis":"Luffy and his crew take on the Villain All-Stars in a game of soccer in order to become the Dream Soccer King. The game comes down to a pk tie-breaker shoot-out with Coby as goalie and Helmeppo refereeing.\n\n(Source: ANN)","background":null,"season":null,"year":null,"broadcast":{"day":null,"time":null,"timezone":null,"string":null},"producers":[],"licensors":[],"studios":[{"mal_id":18,"type":"anime","name":"Toei Animation","url":"https:\/\/myanimelist.net\/anime\/producer\/18\/Toei_Animation"}],"genres":[{"mal_id":4,"type":"anime","name":"Comedy","url":"https:\/\/myanimelist.net\/anime\/genre\/4\/Comedy"},{"mal_id":10,"type":"anime","name":"Fantasy","url":"https:\/\/myanimelist.net\/anime\/genre\/10\/Fantasy"},{"mal_id":30,"type":"anime","name":"Sports","url":"https:\/\/myanimelist.net\/anime\/genre\/30\/Sports"}],"explicit_genres":[],"themes":[{"mal_id":77,"type":"anime","name":"Team Sports","url":"https:\/\/myanimelist.net\/anime\/genre\/77\/Team_Sports"}],"demographics":[{"mal_id":27,"type":"anime","name":"Shounen","url":"https:\/\/myanimelist.net\/anime\/genre\/27\/Shounen"}],"relations":[{"relation":"Full story","entry":[{"mal_id":21,"type":"anime","name":"One Piece","url":"https:\/\/myanimelist.net\/anime\/21\/One_Piece"}]},{"relation":"Parent story","entry":[{"mal_id":461,"type":"anime","name":"One Piece Movie 03: Chinjuu-jima no Chopper Oukoku","url":"https:\/\/myanimelist.net\/anime\/461\/One_Piece_Movie_03__Chinjuu-jima_no_Chopper_Oukoku"}]}],"theme":{"openings":[],"endings":[]},"external":[{"name":"Official Site","url":"http:\/\/www.toei-anim.co.jp\/movie\/2002_spring\/one.html"},{"name":"AniDB","url":"https:\/\/anidb.net\/perl-bin\/animedb.pl?show=anime&aid=1253"},{"name":"ANN","url":"https:\/\/www.animenewsnetwork.com\/encyclopedia\/anime.php?id=6528"}],"streaming":[]}}