{"data":{"mal_id":780,"url":"https:\/\/myanimelist.net\/anime\/780\/Detective_Conan_Movie_02__The_Fourteenth_Target","images":{"jpg":{"image_url":"https:\/\/cdn.myanimelist.net\/images\/anime\/1900\/94316.jpg","small_image_url":"https:\/\/cdn.myanimelist.net\/images\/anime\/1900\/94316t.jpg","large_image_url":"https:\/\/cdn.myanimelist.net\/images\/anime\/1900\/94316l.jpg"},"webp":{"image_url":"https:\/\/cdn.myanimelist.net\/images\/anime\/1900\/94316.webp","small_image_url":"https:\/\/cdn.myanimelist.net\/images\/anime\/1900\/94316t.webp","large_image_url":"https:\/\/cdn.myanimelist.net\/images\/anime\/1900\/94316l.webp"}},"trailer":{"youtube_id":null,"url":null,"embed_url":null,"images":{"image_url":null,"small_image_url":null,"medium_image_url":null,"large_image_url":null,"maximum_image_url":null}},"approved":true,"titles":[{"type":"Default","title":"Detective Conan Movie 02: The Fourteenth Target"},{"type":"Synonym","title":"Meitantei Conan: Jyuuyonbanme no Target"},{"type":"Japanese","title":"\u540d\u63a2\u5075\u30b3\u30ca\u30f3 \uff11\uff14\u756a\u76ee\u306e\u6a19\u7684"},{"type":"English","title":"Case Closed: The Fourteenth Target"},{"type":"German","title":"Detektiv Conan Film 2: Das 14. Ziel"},{"type":"Spanish","title":"Detective Conan Pel\u00edcula 2: La Decimocuarta V\u00edctima"},{"type":"French","title":"D\u00e9tective Conan Film 2: La Quatorzi\u00e8me Cible"}],"title":"Detective Conan Movie 02: The Fourteenth Target","title_english":"Case Closed: The Fourteenth Target","title_japanese":"\u540d\u63a2\u5075\u30b3\u30ca\u30f3 \uff11\uff14\u756a\u76ee\u306e\u6a19\u7684","title_synonyms":["Meitantei Conan: Jyuuyonbanme no Target"],"type":"Movie","source":"Manga","episodes":1,"status":"Finished Airing","airing":false,"aired":{"from":"1998-04-18T00:00:00+00:00","to":null,"prop":{"from":{"day":18,"month":4,"year":1998},"to":{"day":null,"month":null,"year":null}},"string":"Apr 18, 1998"},"duration":"1 hr 39 min","rating":"PG-13 - Teens 13 or older","score":7.88,"scored_by":38419,"rank":798,"popularity":2668,"members":62680,"favorites":71,"synopsis":"A mysterious attacker has appeared and is assaulting people whose names contain a number from the standard deck of cards in descending order. When Conan Edogawa points out that all the victims are related to the now famous detective Kogorou Mouri, suspicion immediately falls upon the recently released convict Jou Murakami, as Kogorou was the one responsible for his arrest ten years prior.\n\nWith potential victims still at risk, Conan and the police are determined to catch the culprit. As the case gradually unfolds, both Conan and his friend Ran Mouri learn more about her parents' separation and the truth on what transpired a decade ago.\n\n[Written by MAL Rewrite]","background":null,"season":null,"year":null,"broadcast":{"day":null,"time":null,"timezone":null,"string":null},"producers":[],"licensors":[{"mal_id":102,"type":"anime","name":"Funimation","url":"https:\/\/myanimelist.net\/anime\/producer\/102\/Funimation"}],"studios":[{"mal_id":73,"type":"anime","name":"TMS Entertainment","url":"https:\/\/myanimelist.net\/anime\/producer\/73\/TMS_Entertainment"}],"genres":[{"mal_id":2,"type":"anime","name":"Adventure","url":"https:\/\/myanimelist.net\/anime\/genre\/2\/Adventure"},{"mal_id":4,"type":"anime","name":"Comedy","url":"https:\/\/myanimelist.net\/anime\/genre\/4\/Comedy"},{"mal_id":7,"type":"anime","name":"Mystery","url":"https:\/\/myanimelist.net\/anime\/genre\/7\/Mystery"}],"explicit_genres":[],"themes":[{"mal_id":39,"type":"anime","name":"Detective","url":"https:\/\/myanimelist.net\/anime\/genre\/39\/Detective"}],"demographics":[{"mal_id":27,"type":"anime","name":"Shounen","url":"https:\/\/myanimelist.net\/anime\/genre\/27\/Shounen"}],"relations":[{"relation":"Parent story","entry":[{"mal_id":235,"type":"anime","name":"Detective Conan","url":"https:\/\/myanimelist.net\/anime\/235\/Detective_Conan"}]}],"theme":{"openings":[],"endings":["\"\u5c11\u5973\u306e\u9803\u306b\u623e\u3063\u305f\u307f\u305f\u3044\u306b (Shoujo no Koro ni Modotta Mitai ni)\" by ZARD"]},"external":[{"name":"AniDB","url":"https:\/\/anidb.net\/perl-bin\/animedb.pl?show=anime&aid=2645"},{"name":"ANN","url":"https:\/\/www.animenewsnetwork.com\/encyclopedia\/anime.php?id=3757"},{"name":"Wikipedia","url":"http:\/\/en.wikipedia.org\/wiki\/Case_Closed:_The_Fourteenth_Target"}],"streaming":[{"name":"Crunchyroll","url":"http:\/\/www.crunchyroll.com\/series-281139"}]}}